qtypes/__init__.py
qtypes/_base.py
qtypes/_bool.py
qtypes/_button.py
qtypes/_enum.py
qtypes/_float.py
qtypes/_integer.py
qtypes/_null.py
qtypes/_string.py
qtypes/_styles.py
qtypes/_units.py
qtypes/_widgets/__init__.py
qtypes/_widgets/_bool.py
qtypes/_widgets/_button.py
qtypes/_widgets/_enum.py
qtypes/_widgets/_float.py
qtypes/_widgets/_integer.py
qtypes/_widgets/_null.py
qtypes/_widgets/_string.py
qtypes/_widgets/_tree_widget.py
qtypes/examples/__main__.py
qtypes/examples/dynamic.py
qtypes/examples/fs.py
qtypes/examples/one_of_each.py
qtypes/examples/units.py
qtypes/graphics/branch-closed.png
qtypes/graphics/branch-end.png
qtypes/graphics/branch-more.png
qtypes/graphics/branch-open.png
qtypes/graphics/vline.png
qtypes/styles/tomorrow-night/QApplication.qss
qtypes/styles/tomorrow-night/QCheckBox.qss
qtypes/styles/tomorrow-night/QComboBox.qss
qtypes/styles/tomorrow-night/QDoubleSpinBox.qss
qtypes/styles/tomorrow-night/QFrame.qss
qtypes/styles/tomorrow-night/QLineEdit.qss
qtypes/styles/tomorrow-night/QPushButton.qss
qtypes/styles/tomorrow-night/QSpinBox.qss
qtypes/styles/tomorrow-night/QTreeView.qss
qtypes/styles/tomorrow-night/branch-closed.png
qtypes/styles/tomorrow-night/branch-end.png
qtypes/styles/tomorrow-night/branch-more.png
qtypes/styles/tomorrow-night/branch-open.png
qtypes/styles/tomorrow-night/checkbox-disabled-checked.png
qtypes/styles/tomorrow-night/checkbox-disabled.png
qtypes/styles/tomorrow-night/checkbox-enabled-checked.png
qtypes/styles/tomorrow-night/checkbox-enabled.png
qtypes/styles/tomorrow-night/vline.png
qtypes-2023.3.0.dist-info/LICENSE
qtypes-2023.3.0.dist-info/WHEEL
qtypes-2023.3.0.dist-info/METADATA
qtypes-2023.3.0.dist-info/RECORD
