Metadata-Version: 2.1
Name: qtypes
Version: 2023.3.0
Summary: Build qt graphical user interfaces out of simple type objects.
Home-page: https://gitlab.com/yaq/qtypes
Author: Blaise Thompson
Author-email: blaise@untzag.com
Classifier: Development Status :: 2 - Pre-Alpha
Classifier: Intended Audience :: Science/Research
Classifier: License :: OSI Approved :: GNU Lesser General Public License v3 (LGPLv3)
Classifier: Natural Language :: English
Classifier: Programming Language :: Python :: 3
Classifier: Programming Language :: Python :: 3.7
Classifier: Programming Language :: Python :: 3.8
Classifier: Programming Language :: Python :: 3.9
Classifier: Programming Language :: Python :: 3.10
Classifier: Topic :: Scientific/Engineering
Requires-Dist: qtpy
Requires-Dist: pint
Requires-Dist: black ; extra == "dev"
Requires-Dist: pre-commit ; extra == "dev"
Requires-Dist: pyside2>=5.12 ; extra == "test"
Requires-Dist: pytest ; extra == "test"
Project-URL: Issues, https://gitlab.com/yaq/qtypes/issues
Project-URL: Source, https://gitlab.com/yaq/qtypes
Provides-Extra: dev
Provides-Extra: test
